witty/__init__.py
witty/compile_module.py
witty-0.3.1.dist-info/licenses/LICENSE
witty-0.3.1.dist-info/METADATA
witty-0.3.1.dist-info/WHEEL
witty-0.3.1.dist-info/top_level.txt
witty-0.3.1.dist-info/RECORD
