Metadata-Version: 2.4
Name: witty
Version: 0.3.1
Summary: Well-in-Time Compiler for Cython Modules
Author-email: Jan Funke <funkej@janelia.hhmi.org>, Talley Lambert <talley.lambert@gmail.com>
License: BSD 3-Clause License
Project-URL: homepage, https://github.com/funkelab/witty
Project-URL: repository, https://github.com/funkelab/witty
Classifier: License :: OSI Approved :: BSD License
Classifier: Programming Language :: Python :: 3
Classifier: Programming Language :: Python :: 3.9
Classifier: Programming Language :: Python :: 3.10
Classifier: Programming Language :: Python :: 3.11
Classifier: Programming Language :: Python :: 3.12
Classifier: Programming Language :: Python :: 3.13
Classifier: Typing :: Typed
Requires-Python: >=3.9
License-File: LICENSE
Requires-Dist: Cython<3.2,>=3.0
Requires-Dist: setuptools
Requires-Dist: nanobind
Provides-Extra: cython
Requires-Dist: Cython<3.2,>=3.0; extra == "cython"
Provides-Extra: nanobind
Requires-Dist: nanobind; extra == "nanobind"
Dynamic: license-file
